golem/__init__.py
golem/actions.py
golem/browser.py
golem/execution.py
golem/helpers.py
golem/main.py
golem/bin/__init__.py
golem/bin/golem_admin.py
golem/bin/golem_init.py
golem/bin/golem_standalone.py
golem/cli/__init__.py
golem/cli/argument_parser.py
golem/cli/commands.py
golem/cli/messages.py
golem/core/__init__.py
golem/core/environment_manager.py
golem/core/errors.py
golem/core/exceptions.py
golem/core/file_manager.py
golem/core/lock.py
golem/core/page.py
golem/core/parsing_utils.py
golem/core/project.py
golem/core/secrets_manager.py
golem/core/session.py
golem/core/settings_manager.py
golem/core/suite.py
golem/core/tags_manager.py
golem/core/test.py
golem/core/test_data.py
golem/core/test_directory.py
golem/core/test_parser.py
golem/core/utils.py
golem/execution_runner/__init__.py
golem/execution_runner/execution_runner.py
golem/execution_runner/interactive.py
golem/execution_runner/multiprocess_executor.py
golem/gui/__init__.py
golem/gui/api.py
golem/gui/gui_start.py
golem/gui/gui_utils.py
golem/gui/report.py
golem/gui/user_management.py
golem/gui/web_app.py
golem/gui/static/css/code-editor-common.css
golem/gui/static/css/json_code_editor.css
golem/gui/static/css/list_common.css
golem/gui/static/css/main.css
golem/gui/static/css/page_object.css
golem/gui/static/css/report.css
golem/gui/static/css/suite.css
golem/gui/static/css/test_case.css
golem/gui/static/css/test_case_code.css
golem/gui/static/css/test_case_common.css
golem/gui/static/css/bootstrap/bootstrap-theme.min.css
golem/gui/static/css/bootstrap/bootstrap.min.css
golem/gui/static/css/font-awesome/font-awesome.min.css
golem/gui/static/css/fonts/FontAwesome.otf
golem/gui/static/css/fonts/fontawesome-webfont.eot
golem/gui/static/css/fonts/fontawesome-webfont.svg
golem/gui/static/css/fonts/fontawesome-webfont.ttf
golem/gui/static/css/fonts/fontawesome-webfont.woff
golem/gui/static/css/fonts/fontawesome-webfont.woff2
golem/gui/static/css/fonts/glyphicons-halflings-regular.eot
golem_framework-0.10.1.dist-info/LICENSE
golem_framework-0.10.1.dist-info/METADATA
golem_framework-0.10.1.dist-info/WHEEL
golem_framework-0.10.1.dist-info/entry_points.txt
golem_framework-0.10.1.dist-info/top_level.txt
golem_framework-0.10.1.dist-info/RECORD
