Metadata-Version: 2.1
Name: golem-framework
Version: 0.10.1
Summary: Test automation framework for functional tests using Selenium
Home-page: https://github.com/golemhq/golem
Author: Luciano Renzi
Author-email: luciano@lucianorenzi.com
License: MIT
Keywords: test automation framework selenium webdriver
Platform: any
Classifier: Development Status :: 4 - Beta
Classifier: Programming Language :: Python :: 3.4
Classifier: Programming Language :: Python :: 3.5
Classifier: Programming Language :: Python :: 3.6
Classifier: Natural Language :: English
Classifier: Intended Audience :: Developers
Classifier: License :: OSI Approved :: MIT License
Classifier: Operating System :: OS Independent
Classifier: Topic :: Software Development :: Quality Assurance
Classifier: Topic :: Software Development :: Testing
Requires-Dist: Flask (>=0.12.2)
Requires-Dist: Flask-login (>=0.4.0)
Requires-Dist: selenium (<4.0.0a1,>=3.6.0)
Requires-Dist: requests (>=2.18.4)
Requires-Dist: py-webdriver-manager
Requires-Dist: colorama
Provides-Extra: testing
Requires-Dist: pytest ; extra == 'testing'
